pfxposter/__init__.py
pfxposter/__main__.py
pfxposter/poster.py
pfxposter-0.1.6.dist-info/LICENSE
pfxposter-0.1.6.dist-info/METADATA
pfxposter-0.1.6.dist-info/WHEEL
pfxposter-0.1.6.dist-info/entry_points.txt
pfxposter-0.1.6.dist-info/top_level.txt
pfxposter-0.1.6.dist-info/RECORD
