Metadata-Version: 2.1
Name: pfxposter
Version: 0.1.6
Summary: A simple PixelFed to Mastodon/Twitter crossposter
Home-page: https://github.com/ooguz/pfxposter
Author: Özcan Oğuz
Author-email: ozcan@oyd.org.tr
License: GLWTS(Good Luck With That Shit) Public License
Project-URL: Bug Tracker, https://github.com/ooguz/pfxposter/issues
Project-URL: Source Code, https://github.com/ooguz/pfxposter
Platform: UNKNOWN
Classifier: Development Status :: 4 - Beta
Classifier: Environment :: No Input/Output (Daemon)
Classifier: Intended Audience :: Developers
Classifier: License :: Public Domain
Classifier: Operating System :: POSIX :: Linux
Classifier: Programming Language :: Python :: 3.6
Classifier: Programming Language :: Python :: Implementation :: PyPy
Classifier: Topic :: Internet
Requires-Python: >=3.6
Requires-Dist: Mastodon.py (>=1.5.1)
Requires-Dist: atoma (>=0.0.17)
Requires-Dist: toml (>=0.10.1)
Requires-Dist: python-crontab (>=2.5.1)
Requires-Dist: requests
